MySQL/__init__.py
MySQL/mysql_easy.py
mysql_connector_easy-0.5.dist-info/METADATA
mysql_connector_easy-0.5.dist-info/WHEEL
mysql_connector_easy-0.5.dist-info/top_level.txt
mysql_connector_easy-0.5.dist-info/RECORD
